django_nest/__init__.py
django_nest/__main__.py
django_nest/public/django_nest/img/logo.png
django_nest-1.0.1.dist-info/METADATA
django_nest-1.0.1.dist-info/WHEEL
django_nest-1.0.1.dist-info/RECORD
