Metadata-Version: 2.1
Name: django-nest
Version: 1.0.1
Summary: DjangoNest: A Python CMS with the Elegance of Django DjangoNest is a Content Management System (CMS) built with a powerful combination of Python and Django, providing an agile and flexible development experience. The project was born from the need to create an intuitive solution for efficient content management in web environments.
Home-page: https://github.com/TechFourGood/django_nest
License: MIT
Author: pratadaniel94
Author-email: danielprata@outlook.com
Requires-Python: >=3.8,<4.0
Classifier: License :: OSI Approved :: MIT License
Classifier: Programming Language :: Python :: 3
Classifier: Programming Language :: Python :: 3.8
Classifier: Programming Language :: Python :: 3.9
Classifier: Programming Language :: Python :: 3.10
Classifier: Programming Language :: Python :: 3.11
Classifier: Programming Language :: Python :: 3.12
Requires-Dist: gitpython (>=3.1.41,<4.0.0)
Requires-Dist: requests (>=2.31.0,<3.0.0)
Project-URL: Repository, https://github.com/TechFourGood/django_nest
